install_concierge/__init__.py
install_concierge/install.py
install_concierge/relaunch.py
install_concierge/docker_compose/docker-compose-launch-keycloak.yml
install_concierge/docker_compose/docker-compose.yml
install_concierge/docker_compose/docker_compose_dependencies/docker-compose-blank.yml
install_concierge/docker_compose/docker_compose_dependencies/docker-compose-concierge.yml
install_concierge/docker_compose/docker_compose_dependencies/docker-compose-keycloak.yml
install_concierge/docker_compose/docker_compose_dependencies/docker-compose-ollama.yml
install_concierge/docker_compose/docker_compose_dependencies/docker-compose-opensearch.yml
install_concierge/docker_compose/docker_compose_dependencies/keycloak_import/concierge-keycloak-realm.json
install_concierge/docker_compose/docker_compose_dependencies/keycloak_javascript/concierge.jar
install_concierge/docker_compose/docker_compose_dependencies/opensearch_config/opensearch.yml
install_concierge/docker_compose/docker_compose_dependencies/opensearch_config/opensearch-security/config.yml
install_concierge/docker_compose/docker_compose_dependencies/opensearch_config/opensearch-security/internal_users.yml
install_concierge/docker_compose/docker_compose_dependencies/opensearch_config/opensearch-security/roles_mapping.yml
install_concierge/installer_lib/__init__.py
install_concierge/installer_lib/arguments.py
install_concierge/installer_lib/clean_up_existing.py
install_concierge/installer_lib/concierge_launcher.py
install_concierge/installer_lib/create_certificates.py
install_concierge/installer_lib/do_install.py
install_concierge/installer_lib/docker_compose_helper.py
install_concierge/installer_lib/docker_containers.py
install_concierge/installer_lib/install_demo_users.py
install_concierge/installer_lib/package_dir.py
install_concierge/installer_lib/set_env.py
install_concierge/installer_lib/upgrade_scripts.py
install_concierge-0.5a13.dist-info/METADATA
install_concierge-0.5a13.dist-info/WHEEL
install_concierge-0.5a13.dist-info/RECORD
