Metadata-Version: 2.3
Name: install-concierge
Version: 0.5a13
Requires-Python: >=3.10
Requires-Dist: concierge-util~=0.2a2
Requires-Dist: cryptography
Requires-Dist: isi-util~=0.2a1
Requires-Dist: packaging
Requires-Dist: python-dotenv
Requires-Dist: requests
Requires-Dist: script-builder~=0.2a1
